magql/__init__.py
magql/check_delete.py
magql/filters.py
magql/nodes.py
magql/py.typed
magql/scalars.py
magql/schema.py
magql/search.py
magql/testing.py
magql/validators.py
magql-1.1.1.dist-info/LICENSE.txt
magql-1.1.1.dist-info/WHEEL
magql-1.1.1.dist-info/METADATA
magql-1.1.1.dist-info/RECORD
