Metadata-Version: 2.1
Name: magql
Version: 1.1.1
Summary: The magical GraphQL framework that generates an API for your data.
Author: David Lord
Requires-Python: >=3.10
Requires-Dist: graphql-core>=3
Requires-Dist: python-dateutil
Project-URL: Changes, https://magql.autoinvent.dev/page/changes/
Project-URL: Documentation, https://magql.autoinvent.dev
Project-URL: Source, https://github.com/autoinvent/magql
